interface_mixins
