Metadata-Version: 1.1
Name: interface-mixins
Version: 0.0.2
Summary: Interfaces for Python
Home-page: https://www.github.com/zeckalpha/interface-mixins
Author: Kyle Marek-Spartz
Author-email: kyle.marek.spartz@gmail.com
License: MIT
Platform: UNKNOWN
Classifier: Development Status :: 3 - Alpha
Classifier: Intended Audience :: Developers
Classifier: License :: OSI Approved :: MIT License
Classifier: Programming Language :: Python :: 2.7
